jaseci/__init__.py
jaseci-2.2.11.dist-info/METADATA
jaseci-2.2.11.dist-info/WHEEL
jaseci-2.2.11.dist-info/top_level.txt
jaseci-2.2.11.dist-info/RECORD
