Metadata-Version: 2.4
Name: jaseci
Version: 2.2.11
Summary: Jaseci - A complete AI-native programming ecosystem with Jac language, LLM integration, and full-stack web apps
Author-email: Jason Mars <jason@mars.ninja>
Maintainer-email: Jason Mars <jason@mars.ninja>
License-Expression: MIT
Project-URL: Repository, https://github.com/Jaseci-Labs/jaseci
Project-URL: Homepage, https://jaseci.org
Project-URL: Documentation, https://jac-lang.org
Keywords: jac,jaclang,jaseci,ai,llm,full-stack,web-apps,jac-client,jac-scale,programming-language,machine-learning,artificial-intelligence
Requires-Python: >=3.11
Requires-Dist: jaclang>=0.9.13
Requires-Dist: byllm>=0.4.17
Requires-Dist: jac-client>=0.2.13
Requires-Dist: jac-scale>=0.1.4
Requires-Dist: jac-super>=0.1.0
